XinGainianMoniDianlu2FufankuiHeYunsuanFangdaqiJichuFix1/README.md
XinGainianMoniDianlu2FufankuiHeYunsuanFangdaqiJichuFix1/__init__.py
XinGainianMoniDianlu2FufankuiHeYunsuanFangdaqiJichuFix1/__main__.py
XinGainianMoniDianlu2FufankuiHeYunsuanFangdaqiJichuFix1/file.pdf
XinGainianMoniDianlu2FufankuiHeYunsuanFangdaqiJichuFix1/index.html
xin_gainian_moni_dianlu_2_fufankui_he_yunsuan_fangdaqi_jichu_fix1-2025.3.24.0.dist-info/METADATA
xin_gainian_moni_dianlu_2_fufankui_he_yunsuan_fangdaqi_jichu_fix1-2025.3.24.0.dist-info/WHEEL
xin_gainian_moni_dianlu_2_fufankui_he_yunsuan_fangdaqi_jichu_fix1-2025.3.24.0.dist-info/entry_points.txt
xin_gainian_moni_dianlu_2_fufankui_he_yunsuan_fangdaqi_jichu_fix1-2025.3.24.0.dist-info/top_level.txt
xin_gainian_moni_dianlu_2_fufankui_he_yunsuan_fangdaqi_jichu_fix1-2025.3.24.0.dist-info/RECORD
