Metadata-Version: 2.1
Name: xin-gainian-moni-dianlu-2-fufankui-he-yunsuan-fangdaqi-jichu-fix1
Version: 2025.3.24.0
Summary: 新概念模拟电路2-负反馈和运算放大器基础
Home-page: https://github.com/apachecn/xin-gainian-moni-dianlu-2-fufankui-he-yunsuan-fangdaqi-jichu-fix1
Author: ApacheCN
Author-email: apachecn@163.com
Classifier: Development Status :: 4 - Beta
Classifier: Environment :: Console
Classifier: Intended Audience :: Developers
Classifier: Intended Audience :: End Users/Desktop
Classifier: License :: Other/Proprietary License
Classifier: Natural Language :: Chinese (Simplified)
Classifier: Natural Language :: English
Classifier: Operating System :: OS Independent
Classifier: Programming Language :: Python :: 3
Classifier: Programming Language :: Python :: 3 :: Only
Classifier: Programming Language :: Python :: 3.6
Classifier: Programming Language :: Python :: 3.7
Classifier: Topic :: Text Processing :: Markup :: Markdown
Classifier: Topic :: Text Processing :: Markup :: HTML
Classifier: Topic :: Internet :: WWW/HTTP
Classifier: Topic :: Software Development :: Documentation
Classifier: Topic :: Documentation
Requires-Python: >=3.6
